audify/__init__.py
audify-0.0.3.dist-info/LICENSE
audify-0.0.3.dist-info/METADATA
audify-0.0.3.dist-info/WHEEL
audify-0.0.3.dist-info/entry_points.txt
audify-0.0.3.dist-info/top_level.txt
audify-0.0.3.dist-info/RECORD
