Metadata-Version: 2.1
Name: audify
Version: 0.0.3
Summary: A simple command line tool to transform text to speech with AWS.
Home-page: https://github.com/JordonPhillips/audify
Author: Jordon Phillips
Author-email: pypi@jkphillips.me
License: MIT
Keywords: aws polly tts
Platform: UNKNOWN
Classifier: Development Status :: 2 - Pre-Alpha
Classifier: Intended Audience :: Developers
Classifier: Natural Language :: English
Classifier: License :: OSI Approved :: Apache Software License
Classifier: Programming Language :: Python :: 3
Classifier: Programming Language :: Python :: 3.7
Requires-Dist: boto3 (>=1.9.75<2.0.0)
Requires-Dist: pydub (<1.0.0,>=0.23.0)
